bbrio_package/__init__.py
bbrio_package/chi_output.py
chi_final-0.0.6.dist-info/LICENSE.txt
chi_final-0.0.6.dist-info/METADATA
chi_final-0.0.6.dist-info/WHEEL
chi_final-0.0.6.dist-info/top_level.txt
chi_final-0.0.6.dist-info/RECORD
